<?xml version="1.0" encoding="UTF-8" standalone="yes"?>
<phongs>
    <phong id="P255">
        <slVip>10</slVip>
        <slThuong>20</slThuong>
        <slDoi>10</slDoi>
        <dsGheThuong>
            <entry>
                <key>P255A8</key>
                <value>
                    <gia>80000.0</gia>
                    <loai>Thuong</loai>
                    <viTri>P255A8</viTri>
                </value>
            </entry>
            <entry>
                <key>P255B9</key>
                <value>
                    <gia>80000.0</gia>
                    <loai>Thuong</loai>
                    <viTri>P255B9</viTri>
                </value>
            </entry>
            <entry>
                <key>P255A7</key>
                <value>
                    <gia>80000.0</gia>
                    <loai>Thuong</loai>
                    <viTri>P255A7</viTri>
                </value>
            </entry>
            <entry>
                <key>P255B8</key>
                <value>
                    <gia>80000.0</gia>
                    <loai>Thuong</loai>
                    <viTri>P255B8</viTri>
                </value>
            </entry>
            <entry>
                <key>P255A9</key>
                <value>
                    <gia>80000.0</gia>
                    <loai>Thuong</loai>
                    <viTri>P255A9</viTri>
                </value>
            </entry>
            <entry>
                <key>P255A4</key>
                <value>
                    <gia>80000.0</gia>
                    <loai>Thuong</loai>
                    <viTri>P255A4</viTri>
                </value>
            </entry>
            <entry>
                <key>P255B5</key>
                <value>
                    <gia>80000.0</gia>
                    <loai>Thuong</loai>
                    <viTri>P255B5</viTri>
                </value>
            </entry>
            <entry>
                <key>P255A3</key>
                <value>
                    <gia>80000.0</gia>
                    <loai>Thuong</loai>
                    <viTri>P255A3</viTri>
                </value>
            </entry>
            <entry>
                <key>P255B4</key>
                <value>
                    <gia>80000.0</gia>
                    <khachId>K1</khachId>
                    <loai>Thuong</loai>
                    <viTri>P255B4</viTri>
                </value>
            </entry>
            <entry>
                <key>P255A6</key>
                <value>
                    <gia>80000.0</gia>
                    <loai>Thuong</loai>
                    <viTri>P255A6</viTri>
                </value>
            </entry>
            <entry>
                <key>P255B7</key>
                <value>
                    <gia>80000.0</gia>
                    <loai>Thuong</loai>
                    <viTri>P255B7</viTri>
                </value>
            </entry>
            <entry>
                <key>P255A5</key>
                <value>
                    <gia>80000.0</gia>
                    <loai>Thuong</loai>
                    <viTri>P255A5</viTri>
                </value>
            </entry>
            <entry>
                <key>P255B6</key>
                <value>
                    <gia>80000.0</gia>
                    <loai>Thuong</loai>
                    <viTri>P255B6</viTri>
                </value>
            </entry>
            <entry>
                <key>P255B1</key>
                <value>
                    <gia>80000.0</gia>
                    <loai>Thuong</loai>
                    <viTri>P255B1</viTri>
                </value>
            </entry>
            <entry>
                <key>P255A2</key>
                <value>
                    <gia>80000.0</gia>
                    <loai>Thuong</loai>
                    <viTri>P255A2</viTri>
                </value>
            </entry>
            <entry>
                <key>P255B3</key>
                <value>
                    <gia>80000.0</gia>
                    <loai>Thuong</loai>
                    <viTri>P255B3</viTri>
                </value>
            </entry>
            <entry>
                <key>P255A1</key>
                <value>
                    <gia>80000.0</gia>
                    <loai>Thuong</loai>
                    <viTri>P255A1</viTri>
                </value>
            </entry>
            <entry>
                <key>P255B2</key>
                <value>
                    <gia>80000.0</gia>
                    <loai>Thuong</loai>
                    <viTri>P255B2</viTri>
                </value>
            </entry>
            <entry>
                <key>P255A10</key>
                <value>
                    <gia>80000.0</gia>
                    <loai>Thuong</loai>
                    <viTri>P255A10</viTri>
                </value>
            </entry>
            <entry>
                <key>P255B10</key>
                <value>
                    <gia>80000.0</gia>
                    <loai>Thuong</loai>
                    <viTri>P255B10</viTri>
                </value>
            </entry>
        </dsGheThuong>
        <dsGheVip>
            <entry>
                <key>P255C9</key>
                <value>
                    <gia>120000.0</gia>
                    <loai>Vip</loai>
                    <viTri>P255C9</viTri>
                </value>
            </entry>
            <entry>
                <key>P255C6</key>
                <value>
                    <gia>120000.0</gia>
                    <loai>Vip</loai>
                    <viTri>P255C6</viTri>
                </value>
            </entry>
            <entry>
                <key>P255C10</key>
                <value>
                    <gia>120000.0</gia>
                    <loai>Vip</loai>
                    <viTri>P255C10</viTri>
                </value>
            </entry>
            <entry>
                <key>P255C5</key>
                <value>
                    <gia>120000.0</gia>
                    <loai>Vip</loai>
                    <viTri>P255C5</viTri>
                </value>
            </entry>
            <entry>
                <key>P255C8</key>
                <value>
                    <gia>120000.0</gia>
                    <loai>Vip</loai>
                    <viTri>P255C8</viTri>
                </value>
            </entry>
            <entry>
                <key>P255C7</key>
                <value>
                    <gia>120000.0</gia>
                    <loai>Vip</loai>
                    <viTri>P255C7</viTri>
                </value>
            </entry>
            <entry>
                <key>P255C2</key>
                <value>
                    <gia>120000.0</gia>
                    <loai>Vip</loai>
                    <viTri>P255C2</viTri>
                </value>
            </entry>
            <entry>
                <key>P255C1</key>
                <value>
                    <gia>120000.0</gia>
                    <loai>Vip</loai>
                    <viTri>P255C1</viTri>
                </value>
            </entry>
            <entry>
                <key>P255C4</key>
                <value>
                    <gia>120000.0</gia>
                    <loai>Vip</loai>
                    <viTri>P255C4</viTri>
                </value>
            </entry>
            <entry>
                <key>P255C3</key>
                <value>
                    <gia>120000.0</gia>
                    <loai>Vip</loai>
                    <viTri>P255C3</viTri>
                </value>
            </entry>
        </dsGheVip>
        <dsGheDoi>
            <entry>
                <key>P255D1</key>
                <value>
                    <gia>200000.0</gia>
                    <loai>Doi</loai>
                    <viTri>P255D1</viTri>
                </value>
            </entry>
            <entry>
                <key>P255D7</key>
                <value>
                    <gia>200000.0</gia>
                    <loai>Doi</loai>
                    <viTri>P255D7</viTri>
                </value>
            </entry>
            <entry>
                <key>P255D6</key>
                <value>
                    <gia>200000.0</gia>
                    <loai>Doi</loai>
                    <viTri>P255D6</viTri>
                </value>
            </entry>
            <entry>
                <key>P255D10</key>
                <value>
                    <gia>200000.0</gia>
                    <loai>Doi</loai>
                    <viTri>P255D10</viTri>
                </value>
            </entry>
            <entry>
                <key>P255D9</key>
                <value>
                    <gia>200000.0</gia>
                    <loai>Doi</loai>
                    <viTri>P255D9</viTri>
                </value>
            </entry>
            <entry>
                <key>P255D8</key>
                <value>
                    <gia>200000.0</gia>
                    <loai>Doi</loai>
                    <viTri>P255D8</viTri>
                </value>
            </entry>
            <entry>
                <key>P255D3</key>
                <value>
                    <gia>200000.0</gia>
                    <loai>Doi</loai>
                    <viTri>P255D3</viTri>
                </value>
            </entry>
            <entry>
                <key>P255D2</key>
                <value>
                    <gia>200000.0</gia>
                    <loai>Doi</loai>
                    <viTri>P255D2</viTri>
                </value>
            </entry>
            <entry>
                <key>P255D5</key>
                <value>
                    <gia>200000.0</gia>
                    <loai>Doi</loai>
                    <viTri>P255D5</viTri>
                </value>
            </entry>
            <entry>
                <key>P255D4</key>
                <value>
                    <gia>200000.0</gia>
                    <loai>Doi</loai>
                    <viTri>P255D4</viTri>
                </value>
            </entry>
        </dsGheDoi>
        <isFull>false</isFull>
        <suatChieu id="SCH757">
            <phim id="Ph3">
                <ten>Road House</ten>
                <theLoai>Hanh dong</theLoai>
                <doTuoi>16</doTuoi>
                <posterLink>/Images/bXi6IQiQDHD00JFio5ZSZOeRSBh.jpg</posterLink>
                <dt>200000.0</dt>
                <thoiLuong>PT2H5M</thoiLuong>
                <TgKhoiChieu>2024-11-01</TgKhoiChieu>
            </phim>
            <phongId>P255</phongId>
            <thoiGianChieu>18-04-2024 20:00</thoiGianChieu>
            <dt>80000.0</dt>
            <chieuXong>false</chieuXong>
        </suatChieu>
        <isPlaying>false</isPlaying>
        <columns>1</columns>
        <rows>69</rows>
        <dt>80000.0</dt>
    </phong>
    <phong id="P1">
        <slVip>10</slVip>
        <slThuong>10</slThuong>
        <slDoi>10</slDoi>
        <dsGheThuong>
            <entry>
                <key>P1A5</key>
                <value>
                    <gia>80000.0</gia>
                    <loai>Thuong</loai>
                    <viTri>P1A5</viTri>
                </value>
            </entry>
            <entry>
                <key>P1A4</key>
                <value>
                    <gia>80000.0</gia>
                    <loai>Thuong</loai>
                    <viTri>P1A4</viTri>
                </value>
            </entry>
            <entry>
                <key>P1A10</key>
                <value>
                    <gia>80000.0</gia>
                    <loai>Thuong</loai>
                    <viTri>P1A10</viTri>
                </value>
            </entry>
            <entry>
                <key>P1A7</key>
                <value>
                    <gia>80000.0</gia>
                    <loai>Thuong</loai>
                    <viTri>P1A7</viTri>
                </value>
            </entry>
            <entry>
                <key>P1A6</key>
                <value>
                    <gia>80000.0</gia>
                    <loai>Thuong</loai>
                    <viTri>P1A6</viTri>
                </value>
            </entry>
            <entry>
                <key>P1A1</key>
                <value>
                    <gia>80000.0</gia>
                    <loai>Thuong</loai>
                    <viTri>P1A1</viTri>
                </value>
            </entry>
            <entry>
                <key>P1A3</key>
                <value>
                    <gia>80000.0</gia>
                    <loai>Thuong</loai>
                    <viTri>P1A3</viTri>
                </value>
            </entry>
            <entry>
                <key>P1A2</key>
                <value>
                    <gia>80000.0</gia>
                    <loai>Thuong</loai>
                    <viTri>P1A2</viTri>
                </value>
            </entry>
            <entry>
                <key>P1A9</key>
                <value>
                    <gia>80000.0</gia>
                    <loai>Thuong</loai>
                    <viTri>P1A9</viTri>
                </value>
            </entry>
            <entry>
                <key>P1A8</key>
                <value>
                    <gia>80000.0</gia>
                    <khachId>K1</khachId>
                    <loai>Thuong</loai>
                    <viTri>P1A8</viTri>
                </value>
            </entry>
        </dsGheThuong>
        <dsGheVip>
            <entry>
                <key>P1B6</key>
                <value>
                    <gia>120000.0</gia>
                    <loai>Vip</loai>
                    <viTri>P1B6</viTri>
                </value>
            </entry>
            <entry>
                <key>P1B5</key>
                <value>
                    <gia>120000.0</gia>
                    <loai>Vip</loai>
                    <viTri>P1B5</viTri>
                </value>
            </entry>
            <entry>
                <key>P1B8</key>
                <value>
                    <gia>120000.0</gia>
                    <khachId>K1</khachId>
                    <loai>Vip</loai>
                    <viTri>P1B8</viTri>
                </value>
            </entry>
            <entry>
                <key>P1B7</key>
                <value>
                    <gia>120000.0</gia>
                    <loai>Vip</loai>
                    <viTri>P1B7</viTri>
                </value>
            </entry>
            <entry>
                <key>P1B2</key>
                <value>
                    <gia>120000.0</gia>
                    <loai>Vip</loai>
                    <viTri>P1B2</viTri>
                </value>
            </entry>
            <entry>
                <key>P1B1</key>
                <value>
                    <gia>120000.0</gia>
                    <loai>Vip</loai>
                    <viTri>P1B1</viTri>
                </value>
            </entry>
            <entry>
                <key>P1B4</key>
                <value>
                    <gia>120000.0</gia>
                    <loai>Vip</loai>
                    <viTri>P1B4</viTri>
                </value>
            </entry>
            <entry>
                <key>P1B3</key>
                <value>
                    <gia>120000.0</gia>
                    <khachId>K1</khachId>
                    <loai>Vip</loai>
                    <viTri>P1B3</viTri>
                </value>
            </entry>
            <entry>
                <key>P1B9</key>
                <value>
                    <gia>120000.0</gia>
                    <khachId>K1</khachId>
                    <loai>Vip</loai>
                    <viTri>P1B9</viTri>
                </value>
            </entry>
            <entry>
                <key>P1B10</key>
                <value>
                    <gia>120000.0</gia>
                    <loai>Vip</loai>
                    <viTri>P1B10</viTri>
                </value>
            </entry>
        </dsGheVip>
        <dsGheDoi>
            <entry>
                <key>P1C7</key>
                <value>
                    <gia>200000.0</gia>
                    <loai>Doi</loai>
                    <viTri>P1C7</viTri>
                </value>
            </entry>
            <entry>
                <key>P1C6</key>
                <value>
                    <gia>200000.0</gia>
                    <loai>Doi</loai>
                    <viTri>P1C6</viTri>
                </value>
            </entry>
            <entry>
                <key>P1C9</key>
                <value>
                    <gia>200000.0</gia>
                    <loai>Doi</loai>
                    <viTri>P1C9</viTri>
                </value>
            </entry>
            <entry>
                <key>P1C8</key>
                <value>
                    <gia>200000.0</gia>
                    <loai>Doi</loai>
                    <viTri>P1C8</viTri>
                </value>
            </entry>
            <entry>
                <key>P1C3</key>
                <value>
                    <gia>200000.0</gia>
                    <khachId>K1</khachId>
                    <loai>Doi</loai>
                    <viTri>P1C3</viTri>
                </value>
            </entry>
            <entry>
                <key>P1C2</key>
                <value>
                    <gia>200000.0</gia>
                    <loai>Doi</loai>
                    <viTri>P1C2</viTri>
                </value>
            </entry>
            <entry>
                <key>P1C5</key>
                <value>
                    <gia>200000.0</gia>
                    <khachId>K1</khachId>
                    <loai>Doi</loai>
                    <viTri>P1C5</viTri>
                </value>
            </entry>
            <entry>
                <key>P1C4</key>
                <value>
                    <gia>200000.0</gia>
                    <loai>Doi</loai>
                    <viTri>P1C4</viTri>
                </value>
            </entry>
            <entry>
                <key>P1C1</key>
                <value>
                    <gia>200000.0</gia>
                    <loai>Doi</loai>
                    <viTri>P1C1</viTri>
                </value>
            </entry>
            <entry>
                <key>P1C10</key>
                <value>
                    <gia>200000.0</gia>
                    <loai>Doi</loai>
                    <viTri>P1C10</viTri>
                </value>
            </entry>
        </dsGheDoi>
        <isFull>false</isFull>
        <suatChieu id="SCH40">
            <phim id="Ph3">
                <ten>Road House</ten>
                <theLoai>Hanh dong</theLoai>
                <doTuoi>16</doTuoi>
                <posterLink>/Images/bXi6IQiQDHD00JFio5ZSZOeRSBh.jpg</posterLink>
                <dt>0.0</dt>
                <thoiLuong>PT2H5M</thoiLuong>
                <TgKhoiChieu>2024-11-01</TgKhoiChieu>
            </phim>
            <phongId>P1</phongId>
            <thoiGianChieu>17-04-2024 16:00</thoiGianChieu>
            <dt>0.0</dt>
            <chieuXong>false</chieuXong>
        </suatChieu>
        <isPlaying>false</isPlaying>
        <columns>1</columns>
        <rows>68</rows>
        <dt>320000.0</dt>
    </phong>
    <phong id="P13">
        <slVip>10</slVip>
        <slThuong>10</slThuong>
        <slDoi>10</slDoi>
        <dsGheThuong>
            <entry>
                <key>P13A10</key>
                <value>
                    <gia>80000.0</gia>
                    <loai>Thuong</loai>
                    <viTri>P13A10</viTri>
                </value>
            </entry>
            <entry>
                <key>P13A9</key>
                <value>
                    <gia>80000.0</gia>
                    <loai>Thuong</loai>
                    <viTri>P13A9</viTri>
                </value>
            </entry>
            <entry>
                <key>P13A7</key>
                <value>
                    <gia>80000.0</gia>
                    <loai>Thuong</loai>
                    <viTri>P13A7</viTri>
                </value>
            </entry>
            <entry>
                <key>P13A8</key>
                <value>
                    <gia>80000.0</gia>
                    <loai>Thuong</loai>
                    <viTri>P13A8</viTri>
                </value>
            </entry>
            <entry>
                <key>P13A5</key>
                <value>
                    <gia>80000.0</gia>
                    <loai>Thuong</loai>
                    <viTri>P13A5</viTri>
                </value>
            </entry>
            <entry>
                <key>P13A6</key>
                <value>
                    <gia>80000.0</gia>
                    <loai>Thuong</loai>
                    <viTri>P13A6</viTri>
                </value>
            </entry>
            <entry>
                <key>P13A3</key>
                <value>
                    <gia>80000.0</gia>
                    <loai>Thuong</loai>
                    <viTri>P13A3</viTri>
                </value>
            </entry>
            <entry>
                <key>P13A4</key>
                <value>
                    <gia>80000.0</gia>
                    <loai>Thuong</loai>
                    <viTri>P13A4</viTri>
                </value>
            </entry>
            <entry>
                <key>P13A1</key>
                <value>
                    <gia>80000.0</gia>
                    <loai>Thuong</loai>
                    <viTri>P13A1</viTri>
                </value>
            </entry>
            <entry>
                <key>P13A2</key>
                <value>
                    <gia>80000.0</gia>
                    <loai>Thuong</loai>
                    <viTri>P13A2</viTri>
                </value>
            </entry>
        </dsGheThuong>
        <dsGheVip>
            <entry>
                <key>P13B10</key>
                <value>
                    <gia>120000.0</gia>
                    <loai>Vip</loai>
                    <viTri>P13B10</viTri>
                </value>
            </entry>
            <entry>
                <key>P13B8</key>
                <value>
                    <gia>120000.0</gia>
                    <khachId>K7</khachId>
                    <loai>Vip</loai>
                    <viTri>P13B8</viTri>
                </value>
            </entry>
            <entry>
                <key>P13B9</key>
                <value>
                    <gia>120000.0</gia>
                    <loai>Vip</loai>
                    <viTri>P13B9</viTri>
                </value>
            </entry>
            <entry>
                <key>P13B6</key>
                <value>
                    <gia>120000.0</gia>
                    <loai>Vip</loai>
                    <viTri>P13B6</viTri>
                </value>
            </entry>
            <entry>
                <key>P13B7</key>
                <value>
                    <gia>120000.0</gia>
                    <loai>Vip</loai>
                    <viTri>P13B7</viTri>
                </value>
            </entry>
            <entry>
                <key>P13B4</key>
                <value>
                    <gia>120000.0</gia>
                    <loai>Vip</loai>
                    <viTri>P13B4</viTri>
                </value>
            </entry>
            <entry>
                <key>P13B5</key>
                <value>
                    <gia>120000.0</gia>
                    <loai>Vip</loai>
                    <viTri>P13B5</viTri>
                </value>
            </entry>
            <entry>
                <key>P13B2</key>
                <value>
                    <gia>120000.0</gia>
                    <loai>Vip</loai>
                    <viTri>P13B2</viTri>
                </value>
            </entry>
            <entry>
                <key>P13B3</key>
                <value>
                    <gia>120000.0</gia>
                    <loai>Vip</loai>
                    <viTri>P13B3</viTri>
                </value>
            </entry>
            <entry>
                <key>P13B1</key>
                <value>
                    <gia>120000.0</gia>
                    <loai>Vip</loai>
                    <viTri>P13B1</viTri>
                </value>
            </entry>
        </dsGheVip>
        <dsGheDoi>
            <entry>
                <key>P13C9</key>
                <value>
                    <gia>200000.0</gia>
                    <loai>Doi</loai>
                    <viTri>P13C9</viTri>
                </value>
            </entry>
            <entry>
                <key>P13C7</key>
                <value>
                    <gia>200000.0</gia>
                    <loai>Doi</loai>
                    <viTri>P13C7</viTri>
                </value>
            </entry>
            <entry>
                <key>P13C8</key>
                <value>
                    <gia>200000.0</gia>
                    <loai>Doi</loai>
                    <viTri>P13C8</viTri>
                </value>
            </entry>
            <entry>
                <key>P13C5</key>
                <value>
                    <gia>200000.0</gia>
                    <loai>Doi</loai>
                    <viTri>P13C5</viTri>
                </value>
            </entry>
            <entry>
                <key>P13C6</key>
                <value>
                    <gia>200000.0</gia>
                    <loai>Doi</loai>
                    <viTri>P13C6</viTri>
                </value>
            </entry>
            <entry>
                <key>P13C3</key>
                <value>
                    <gia>200000.0</gia>
                    <loai>Doi</loai>
                    <viTri>P13C3</viTri>
                </value>
            </entry>
            <entry>
                <key>P13C4</key>
                <value>
                    <gia>200000.0</gia>
                    <loai>Doi</loai>
                    <viTri>P13C4</viTri>
                </value>
            </entry>
            <entry>
                <key>P13C1</key>
                <value>
                    <gia>200000.0</gia>
                    <khachId>K11</khachId>
                    <loai>Doi</loai>
                    <viTri>P13C1</viTri>
                </value>
            </entry>
            <entry>
                <key>P13C10</key>
                <value>
                    <gia>200000.0</gia>
                    <loai>Doi</loai>
                    <viTri>P13C10</viTri>
                </value>
            </entry>
            <entry>
                <key>P13C2</key>
                <value>
                    <gia>200000.0</gia>
                    <khachId>K4</khachId>
                    <loai>Doi</loai>
                    <viTri>P13C2</viTri>
                </value>
            </entry>
        </dsGheDoi>
        <isFull>false</isFull>
        <suatChieu id="SCH70">
            <phim id="Ph1">
                <ten>Godzilla x Kong: The New Empire</ten>
                <theLoai>Khoa hoc vien tuong</theLoai>
                <doTuoi>16</doTuoi>
                <posterLink>/Images/tMefBSflR6PGQLv7WvFPpKLZkyk.jpg</posterLink>
                <dt>200000.0</dt>
                <thoiLuong>PT2H5M</thoiLuong>
                <TgKhoiChieu>2024-07-10</TgKhoiChieu>
            </phim>
            <phongId>P13</phongId>
            <thoiGianChieu>18-04-2024 10:00</thoiGianChieu>
            <dt>200000.0</dt>
            <chieuXong>false</chieuXong>
        </suatChieu>
        <isPlaying>false</isPlaying>
        <columns>1</columns>
        <rows>68</rows>
        <dt>520000.0</dt>
    </phong>
</phongs>
